{
    "sections": {
        "template-product-banner": {
            "type": "template-product-banner",
            "blocks": {
                
            },
            "block_order": ["template-product-banner"]
        },
        "template-slider": {
            "type": "template-slider",
            "blocks": {
                "slider": {
                    "type":"Slider"
                }
               
            },
            "block_order": ["slider"]
        },
        "template-faq": {
            "type": "template-faq",
            "blocks": {
                "FAQ":{
                    "type":"FAQ_item"
                }
            },
            "block_order": ["FAQ"]
        },
        "template-slider-tabs": {
            "type": "template-slider-tabs",
            "blocks": {
                "Slider-tabs":{
                    "type":"slider-tabs"
                }
            },
            "block_order": ["Slider-tabs"]
        },
        "template-policy": {
            "type": "template-policy",
            "blocks": {
                "policy_heading":{
                    "type":"policy_heading"
                },
                "list":{
                    "type":"list"
                }
            },
            "block_order": ["policy_heading","list"]
        },
        "template-card": {
            "type": "template-card",
            "blocks": {
                "cards_title":{
                    "type":"cards_title"
                },
                "card":{
                    "type":"card"
                }
            },
            "block_order": ["cards_title","card"]
        },
        "template-single-banner": {
            "type": "template-single-banner",
            "blocks": {
                "banner_image":{
                    "type":"banner_image"
                }
            },
            "block_order": ["banner_image"]
        }
    },
    "order": [ "template-product-banner","template-slider","template-faq","template-slider-tabs","template-policy","template-card","template-single-banner" ]
}